{"nodes": [{"id": "c_users_reza_documents_publish_docs_06_design_system_md", "label": "06_DESIGN_SYSTEM.md", "file_type": "document", "source_file": "docs/06_DESIGN_SYSTEM.md", "source_location": "L1"}, {"id": "docs_06_design_system_06_design_system_ux_specification", "label": "06 \u2014 Design System & UX Specification", "file_type": "document", "source_file": "docs/06_DESIGN_SYSTEM.md", "source_location": "L1"}, {"id": "docs_06_design_system_table_of_contents", "label": "Table of Contents", "file_type": "document", "source_file": "docs/06_DESIGN_SYSTEM.md", "source_location": "L8"}, {"id": "docs_06_design_system_1_design_principles", "label": "1. Design Principles", "file_type": "document", "source_file": "docs/06_DESIGN_SYSTEM.md", "source_location": "L25"}, {"id": "docs_06_design_system_2_foundations", "label": "2. Foundations", "file_type": "document", "source_file": "docs/06_DESIGN_SYSTEM.md", "source_location": "L45"}, {"id": "docs_06_design_system_2_1_color_tokens_from_globals_css", "label": "2.1 Color tokens (from `globals.css`)", "file_type": "document", "source_file": "docs/06_DESIGN_SYSTEM.md", "source_location": "L47"}, {"id": "docs_06_design_system_2_2_typography", "label": "2.2 Typography", "file_type": "document", "source_file": "docs/06_DESIGN_SYSTEM.md", "source_location": "L83"}, {"id": "docs_06_design_system_2_3_spacing_layout", "label": "2.3 Spacing & layout", "file_type": "document", "source_file": "docs/06_DESIGN_SYSTEM.md", "source_location": "L97"}, {"id": "docs_06_design_system_2_4_radius", "label": "2.4 Radius", "file_type": "document", "source_file": "docs/06_DESIGN_SYSTEM.md", "source_location": "L104"}, {"id": "docs_06_design_system_2_5_shadow", "label": "2.5 Shadow", "file_type": "document", "source_file": "docs/06_DESIGN_SYSTEM.md", "source_location": "L109"}, {"id": "docs_06_design_system_2_6_motion", "label": "2.6 Motion", "file_type": "document", "source_file": "docs/06_DESIGN_SYSTEM.md", "source_location": "L113"}, {"id": "docs_06_design_system_2_7_ambient_background", "label": "2.7 Ambient background", "file_type": "document", "source_file": "docs/06_DESIGN_SYSTEM.md", "source_location": "L120"}, {"id": "docs_06_design_system_3_rtl_persian_first_rules_the_moat", "label": "3. RTL & Persian-First Rules (the moat)", "file_type": "document", "source_file": "docs/06_DESIGN_SYSTEM.md", "source_location": "L127"}, {"id": "docs_06_design_system_3_1_root_setup", "label": "3.1 Root setup", "file_type": "document", "source_file": "docs/06_DESIGN_SYSTEM.md", "source_location": "L132"}, {"id": "docs_06_design_system_3_2_bidirectional_text", "label": "3.2 Bidirectional text", "file_type": "document", "source_file": "docs/06_DESIGN_SYSTEM.md", "source_location": "L139"}, {"id": "docs_06_design_system_3_3_numbers_dates", "label": "3.3 Numbers & dates", "file_type": "document", "source_file": "docs/06_DESIGN_SYSTEM.md", "source_location": "L146"}, {"id": "docs_06_design_system_3_4_iconography_mirroring", "label": "3.4 Iconography mirroring", "file_type": "document", "source_file": "docs/06_DESIGN_SYSTEM.md", "source_location": "L151"}, {"id": "docs_06_design_system_3_5_focus_order", "label": "3.5 Focus order", "file_type": "document", "source_file": "docs/06_DESIGN_SYSTEM.md", "source_location": "L156"}, {"id": "docs_06_design_system_3_6_punctuation", "label": "3.6 Punctuation", "file_type": "document", "source_file": "docs/06_DESIGN_SYSTEM.md", "source_location": "L160"}, {"id": "docs_06_design_system_3_7_token_audit_gate", "label": "3.7 Token audit gate", "file_type": "document", "source_file": "docs/06_DESIGN_SYSTEM.md", "source_location": "L164"}, {"id": "docs_06_design_system_4_jalali_calendar_patterns", "label": "4. Jalali Calendar Patterns", "file_type": "document", "source_file": "docs/06_DESIGN_SYSTEM.md", "source_location": "L170"}, {"id": "docs_06_design_system_4_1_calendar_primitives", "label": "4.1 Calendar primitives", "file_type": "document", "source_file": "docs/06_DESIGN_SYSTEM.md", "source_location": "L172"}, {"id": "docs_06_design_system_4_2_rendering", "label": "4.2 Rendering", "file_type": "document", "source_file": "docs/06_DESIGN_SYSTEM.md", "source_location": "L177"}, {"id": "docs_06_design_system_4_3_date_axes_on_charts", "label": "4.3 Date axes on charts", "file_type": "document", "source_file": "docs/06_DESIGN_SYSTEM.md", "source_location": "L185"}, {"id": "docs_06_design_system_4_4_scheduling_semantics", "label": "4.4 Scheduling semantics", "file_type": "document", "source_file": "docs/06_DESIGN_SYSTEM.md", "source_location": "L189"}, {"id": "docs_06_design_system_5_component_library", "label": "5. Component Library", "file_type": "document", "source_file": "docs/06_DESIGN_SYSTEM.md", "source_location": "L195"}, {"id": "docs_06_design_system_5_1_base_shadcn_ui_new_york_style", "label": "5.1 Base: shadcn/ui (New York style)", "file_type": "document", "source_file": "docs/06_DESIGN_SYSTEM.md", "source_location": "L197"}, {"id": "docs_06_design_system_5_2_nashrino_specific_components", "label": "5.2 Nashrino-specific components", "file_type": "document", "source_file": "docs/06_DESIGN_SYSTEM.md", "source_location": "L202"}, {"id": "docs_06_design_system_5_3_component_conventions", "label": "5.3 Component conventions", "file_type": "document", "source_file": "docs/06_DESIGN_SYSTEM.md", "source_location": "L220"}, {"id": "docs_06_design_system_5_4_long_list_handling", "label": "5.4 Long-list handling", "file_type": "document", "source_file": "docs/06_DESIGN_SYSTEM.md", "source_location": "L231"}, {"id": "docs_06_design_system_6_layout_app_shell", "label": "6. Layout & App Shell", "file_type": "document", "source_file": "docs/06_DESIGN_SYSTEM.md", "source_location": "L238"}, {"id": "docs_06_design_system_6_1_root_structure", "label": "6.1 Root structure", "file_type": "document", "source_file": "docs/06_DESIGN_SYSTEM.md", "source_location": "L240"}, {"id": "docs_06_design_system_6_2_sticky_footer_rule_mandatory", "label": "6.2 Sticky footer rule (mandatory)", "file_type": "document", "source_file": "docs/06_DESIGN_SYSTEM.md", "source_location": "L255"}, {"id": "docs_06_design_system_6_3_mobile", "label": "6.3 Mobile", "file_type": "document", "source_file": "docs/06_DESIGN_SYSTEM.md", "source_location": "L261"}, {"id": "docs_06_design_system_7_view_specifications", "label": "7. View Specifications", "file_type": "document", "source_file": "docs/06_DESIGN_SYSTEM.md", "source_location": "L268"}, {"id": "docs_06_design_system_7_1_dashboard", "label": "7.1 Dashboard (`/`)", "file_type": "document", "source_file": "docs/06_DESIGN_SYSTEM.md", "source_location": "L274"}, {"id": "docs_06_design_system_7_2_compose_compose", "label": "7.2 Compose (`/compose`)", "file_type": "document", "source_file": "docs/06_DESIGN_SYSTEM.md", "source_location": "L285"}, {"id": "docs_06_design_system_7_3_calendar_calendar", "label": "7.3 Calendar (`/calendar`)", "file_type": "document", "source_file": "docs/06_DESIGN_SYSTEM.md", "source_location": "L292"}, {"id": "docs_06_design_system_7_4_campaigns_campaigns", "label": "7.4 Campaigns (`/campaigns`)", "file_type": "document", "source_file": "docs/06_DESIGN_SYSTEM.md", "source_location": "L297"}, {"id": "docs_06_design_system_7_5_content_content", "label": "7.5 Content (`/content`)", "file_type": "document", "source_file": "docs/06_DESIGN_SYSTEM.md", "source_location": "L301"}, {"id": "docs_06_design_system_7_6_media_media", "label": "7.6 Media (`/media`)", "file_type": "document", "source_file": "docs/06_DESIGN_SYSTEM.md", "source_location": "L305"}, {"id": "docs_06_design_system_7_7_inbox_inbox_p2", "label": "7.7 Inbox (`/inbox`) \u2014 P2", "file_type": "document", "source_file": "docs/06_DESIGN_SYSTEM.md", "source_location": "L309"}, {"id": "docs_06_design_system_7_8_analytics_analytics", "label": "7.8 Analytics (`/analytics`)", "file_type": "document", "source_file": "docs/06_DESIGN_SYSTEM.md", "source_location": "L313"}, {"id": "docs_06_design_system_7_9_channels_channels", "label": "7.9 Channels (`/channels`)", "file_type": "document", "source_file": "docs/06_DESIGN_SYSTEM.md", "source_location": "L317"}, {"id": "docs_06_design_system_7_10_settings_store", "label": "7.10 Settings (`/store`)", "file_type": "document", "source_file": "docs/06_DESIGN_SYSTEM.md", "source_location": "L320"}, {"id": "docs_06_design_system_8_interaction_patterns", "label": "8. Interaction Patterns", "file_type": "document", "source_file": "docs/06_DESIGN_SYSTEM.md", "source_location": "L326"}, {"id": "docs_06_design_system_8_1_loading_states", "label": "8.1 Loading states", "file_type": "document", "source_file": "docs/06_DESIGN_SYSTEM.md", "source_location": "L328"}, {"id": "docs_06_design_system_8_2_empty_states", "label": "8.2 Empty states", "file_type": "document", "source_file": "docs/06_DESIGN_SYSTEM.md", "source_location": "L333"}, {"id": "docs_06_design_system_8_3_error_states", "label": "8.3 Error states", "file_type": "document", "source_file": "docs/06_DESIGN_SYSTEM.md", "source_location": "L337"}, {"id": "docs_06_design_system_8_4_toasts_sonner", "label": "8.4 Toasts (sonner)", "file_type": "document", "source_file": "docs/06_DESIGN_SYSTEM.md", "source_location": "L342"}, {"id": "docs_06_design_system_8_5_confirmations", "label": "8.5 Confirmations", "file_type": "document", "source_file": "docs/06_DESIGN_SYSTEM.md", "source_location": "L346"}, {"id": "docs_06_design_system_8_6_drag_and_drop", "label": "8.6 Drag-and-drop", "file_type": "document", "source_file": "docs/06_DESIGN_SYSTEM.md", "source_location": "L350"}, {"id": "docs_06_design_system_8_7_command_palette_cmd_k", "label": "8.7 Command palette (cmd+k)", "file_type": "document", "source_file": "docs/06_DESIGN_SYSTEM.md", "source_location": "L354"}, {"id": "docs_06_design_system_8_8_realtime_feedback", "label": "8.8 Realtime feedback", "file_type": "document", "source_file": "docs/06_DESIGN_SYSTEM.md", "source_location": "L358"}, {"id": "docs_06_design_system_9_accessibility_wcag_2_1_aa", "label": "9. Accessibility (WCAG 2.1 AA)", "file_type": "document", "source_file": "docs/06_DESIGN_SYSTEM.md", "source_location": "L364"}, {"id": "docs_06_design_system_10_responsive_breakpoints", "label": "10. Responsive Breakpoints", "file_type": "document", "source_file": "docs/06_DESIGN_SYSTEM.md", "source_location": "L382"}, {"id": "docs_06_design_system_11_content_voice_persian_ux_writing", "label": "11. Content & Voice (Persian UX writing)", "file_type": "document", "source_file": "docs/06_DESIGN_SYSTEM.md", "source_location": "L399"}, {"id": "docs_06_design_system_12_iconography", "label": "12. Iconography", "file_type": "document", "source_file": "docs/06_DESIGN_SYSTEM.md", "source_location": "L423"}, {"id": "docs_06_design_system_appendix_a_token_quick_reference_from_globals_css", "label": "Appendix A \u2014 Token quick-reference (from `globals.css`)", "file_type": "document", "source_file": "docs/06_DESIGN_SYSTEM.md", "source_location": "L435"}, {"id": "docs_06_design_system_appendix_b_do_don_t", "label": "Appendix B \u2014 Do / Don't", "file_type": "document", "source_file": "docs/06_DESIGN_SYSTEM.md", "source_location": "L457"}], "edges": [{"source": "c_users_reza_documents_publish_docs_06_design_system_md", "target": "docs_06_design_system_06_design_system_ux_specification", "relation": "contains", "confidence": "EXTRACTED", "source_file": "docs/06_DESIGN_SYSTEM.md", "source_location": "L1", "weight": 1.0}, {"source": "docs_06_design_system_06_design_system_ux_specification", "target": "docs_06_design_system_table_of_contents", "relation": "contains", "confidence": "EXTRACTED", "source_file": "docs/06_DESIGN_SYSTEM.md", "source_location": "L8", "weight": 1.0}, {"source": "docs_06_design_system_06_design_system_ux_specification", "target": "docs_06_design_system_1_design_principles", "relation": "contains", "confidence": "EXTRACTED", "source_file": "docs/06_DESIGN_SYSTEM.md", "source_location": "L25", "weight": 1.0}, {"source": "docs_06_design_system_06_design_system_ux_specification", "target": "docs_06_design_system_2_foundations", "relation": "contains", "confidence": "EXTRACTED", "source_file": "docs/06_DESIGN_SYSTEM.md", "source_location": "L45", "weight": 1.0}, {"source": "docs_06_design_system_2_foundations", "target": "docs_06_design_system_2_1_color_tokens_from_globals_css", "relation": "contains", "confidence": "EXTRACTED", "source_file": "docs/06_DESIGN_SYSTEM.md", "source_location": "L47", "weight": 1.0}, {"source": "docs_06_design_system_2_foundations", "target": "docs_06_design_system_2_2_typography", "relation": "contains", "confidence": "EXTRACTED", "source_file": "docs/06_DESIGN_SYSTEM.md", "source_location": "L83", "weight": 1.0}, {"source": "docs_06_design_system_2_foundations", "target": "docs_06_design_system_2_3_spacing_layout", "relation": "contains", "confidence": "EXTRACTED", "source_file": "docs/06_DESIGN_SYSTEM.md", "source_location": "L97", "weight": 1.0}, {"source": "docs_06_design_system_2_foundations", "target": "docs_06_design_system_2_4_radius", "relation": "contains", "confidence": "EXTRACTED", "source_file": "docs/06_DESIGN_SYSTEM.md", "source_location": "L104", "weight": 1.0}, {"source": "docs_06_design_system_2_foundations", "target": "docs_06_design_system_2_5_shadow", "relation": "contains", "confidence": "EXTRACTED", "source_file": "docs/06_DESIGN_SYSTEM.md", "source_location": "L109", "weight": 1.0}, {"source": "docs_06_design_system_2_foundations", "target": "docs_06_design_system_2_6_motion", "relation": "contains", "confidence": "EXTRACTED", "source_file": "docs/06_DESIGN_SYSTEM.md", "source_location": "L113", "weight": 1.0}, {"source": "docs_06_design_system_2_foundations", "target": "docs_06_design_system_2_7_ambient_background", "relation": "contains", "confidence": "EXTRACTED", "source_file": "docs/06_DESIGN_SYSTEM.md", "source_location": "L120", "weight": 1.0}, {"source": "docs_06_design_system_06_design_system_ux_specification", "target": "docs_06_design_system_3_rtl_persian_first_rules_the_moat", "relation": "contains", "confidence": "EXTRACTED", "source_file": "docs/06_DESIGN_SYSTEM.md", "source_location": "L127", "weight": 1.0}, {"source": "c_users_reza_documents_publish_docs_06_design_system_md", "target": "c_users_reza_documents_publish_docs_01_benchmark_analysis_md", "relation": "references", "confidence": "EXTRACTED", "source_file": "docs/06_DESIGN_SYSTEM.md", "source_location": "L130", "weight": 1.0}, {"source": "docs_06_design_system_3_rtl_persian_first_rules_the_moat", "target": "docs_06_design_system_3_1_root_setup", "relation": "contains", "confidence": "EXTRACTED", "source_file": "docs/06_DESIGN_SYSTEM.md", "source_location": "L132", "weight": 1.0}, {"source": "docs_06_design_system_3_rtl_persian_first_rules_the_moat", "target": "docs_06_design_system_3_2_bidirectional_text", "relation": "contains", "confidence": "EXTRACTED", "source_file": "docs/06_DESIGN_SYSTEM.md", "source_location": "L139", "weight": 1.0}, {"source": "docs_06_design_system_3_rtl_persian_first_rules_the_moat", "target": "docs_06_design_system_3_3_numbers_dates", "relation": "contains", "confidence": "EXTRACTED", "source_file": "docs/06_DESIGN_SYSTEM.md", "source_location": "L146", "weight": 1.0}, {"source": "docs_06_design_system_3_rtl_persian_first_rules_the_moat", "target": "docs_06_design_system_3_4_iconography_mirroring", "relation": "contains", "confidence": "EXTRACTED", "source_file": "docs/06_DESIGN_SYSTEM.md", "source_location": "L151", "weight": 1.0}, {"source": "docs_06_design_system_3_rtl_persian_first_rules_the_moat", "target": "docs_06_design_system_3_5_focus_order", "relation": "contains", "confidence": "EXTRACTED", "source_file": "docs/06_DESIGN_SYSTEM.md", "source_location": "L156", "weight": 1.0}, {"source": "docs_06_design_system_3_rtl_persian_first_rules_the_moat", "target": "docs_06_design_system_3_6_punctuation", "relation": "contains", "confidence": "EXTRACTED", "source_file": "docs/06_DESIGN_SYSTEM.md", "source_location": "L160", "weight": 1.0}, {"source": "docs_06_design_system_3_rtl_persian_first_rules_the_moat", "target": "docs_06_design_system_3_7_token_audit_gate", "relation": "contains", "confidence": "EXTRACTED", "source_file": "docs/06_DESIGN_SYSTEM.md", "source_location": "L164", "weight": 1.0}, {"source": "docs_06_design_system_06_design_system_ux_specification", "target": "docs_06_design_system_4_jalali_calendar_patterns", "relation": "contains", "confidence": "EXTRACTED", "source_file": "docs/06_DESIGN_SYSTEM.md", "source_location": "L170", "weight": 1.0}, {"source": "docs_06_design_system_4_jalali_calendar_patterns", "target": "docs_06_design_system_4_1_calendar_primitives", "relation": "contains", "confidence": "EXTRACTED", "source_file": "docs/06_DESIGN_SYSTEM.md", "source_location": "L172", "weight": 1.0}, {"source": "docs_06_design_system_4_jalali_calendar_patterns", "target": "docs_06_design_system_4_2_rendering", "relation": "contains", "confidence": "EXTRACTED", "source_file": "docs/06_DESIGN_SYSTEM.md", "source_location": "L177", "weight": 1.0}, {"source": "docs_06_design_system_4_jalali_calendar_patterns", "target": "docs_06_design_system_4_3_date_axes_on_charts", "relation": "contains", "confidence": "EXTRACTED", "source_file": "docs/06_DESIGN_SYSTEM.md", "source_location": "L185", "weight": 1.0}, {"source": "docs_06_design_system_4_jalali_calendar_patterns", "target": "docs_06_design_system_4_4_scheduling_semantics", "relation": "contains", "confidence": "EXTRACTED", "source_file": "docs/06_DESIGN_SYSTEM.md", "source_location": "L189", "weight": 1.0}, {"source": "docs_06_design_system_06_design_system_ux_specification", "target": "docs_06_design_system_5_component_library", "relation": "contains", "confidence": "EXTRACTED", "source_file": "docs/06_DESIGN_SYSTEM.md", "source_location": "L195", "weight": 1.0}, {"source": "docs_06_design_system_5_component_library", "target": "docs_06_design_system_5_1_base_shadcn_ui_new_york_style", "relation": "contains", "confidence": "EXTRACTED", "source_file": "docs/06_DESIGN_SYSTEM.md", "source_location": "L197", "weight": 1.0}, {"source": "docs_06_design_system_5_component_library", "target": "docs_06_design_system_5_2_nashrino_specific_components", "relation": "contains", "confidence": "EXTRACTED", "source_file": "docs/06_DESIGN_SYSTEM.md", "source_location": "L202", "weight": 1.0}, {"source": "docs_06_design_system_5_component_library", "target": "docs_06_design_system_5_3_component_conventions", "relation": "contains", "confidence": "EXTRACTED", "source_file": "docs/06_DESIGN_SYSTEM.md", "source_location": "L220", "weight": 1.0}, {"source": "docs_06_design_system_5_component_library", "target": "docs_06_design_system_5_4_long_list_handling", "relation": "contains", "confidence": "EXTRACTED", "source_file": "docs/06_DESIGN_SYSTEM.md", "source_location": "L231", "weight": 1.0}, {"source": "docs_06_design_system_06_design_system_ux_specification", "target": "docs_06_design_system_6_layout_app_shell", "relation": "contains", "confidence": "EXTRACTED", "source_file": "docs/06_DESIGN_SYSTEM.md", "source_location": "L238", "weight": 1.0}, {"source": "docs_06_design_system_6_layout_app_shell", "target": "docs_06_design_system_6_1_root_structure", "relation": "contains", "confidence": "EXTRACTED", "source_file": "docs/06_DESIGN_SYSTEM.md", "source_location": "L240", "weight": 1.0}, {"source": "docs_06_design_system_6_layout_app_shell", "target": "docs_06_design_system_6_2_sticky_footer_rule_mandatory", "relation": "contains", "confidence": "EXTRACTED", "source_file": "docs/06_DESIGN_SYSTEM.md", "source_location": "L255", "weight": 1.0}, {"source": "docs_06_design_system_6_layout_app_shell", "target": "docs_06_design_system_6_3_mobile", "relation": "contains", "confidence": "EXTRACTED", "source_file": "docs/06_DESIGN_SYSTEM.md", "source_location": "L261", "weight": 1.0}, {"source": "docs_06_design_system_06_design_system_ux_specification", "target": "docs_06_design_system_7_view_specifications", "relation": "contains", "confidence": "EXTRACTED", "source_file": "docs/06_DESIGN_SYSTEM.md", "source_location": "L268", "weight": 1.0}, {"source": "docs_06_design_system_7_view_specifications", "target": "docs_06_design_system_7_1_dashboard", "relation": "contains", "confidence": "EXTRACTED", "source_file": "docs/06_DESIGN_SYSTEM.md", "source_location": "L274", "weight": 1.0}, {"source": "docs_06_design_system_7_view_specifications", "target": "docs_06_design_system_7_2_compose_compose", "relation": "contains", "confidence": "EXTRACTED", "source_file": "docs/06_DESIGN_SYSTEM.md", "source_location": "L285", "weight": 1.0}, {"source": "docs_06_design_system_7_view_specifications", "target": "docs_06_design_system_7_3_calendar_calendar", "relation": "contains", "confidence": "EXTRACTED", "source_file": "docs/06_DESIGN_SYSTEM.md", "source_location": "L292", "weight": 1.0}, {"source": "docs_06_design_system_7_view_specifications", "target": "docs_06_design_system_7_4_campaigns_campaigns", "relation": "contains", "confidence": "EXTRACTED", "source_file": "docs/06_DESIGN_SYSTEM.md", "source_location": "L297", "weight": 1.0}, {"source": "docs_06_design_system_7_view_specifications", "target": "docs_06_design_system_7_5_content_content", "relation": "contains", "confidence": "EXTRACTED", "source_file": "docs/06_DESIGN_SYSTEM.md", "source_location": "L301", "weight": 1.0}, {"source": "docs_06_design_system_7_view_specifications", "target": "docs_06_design_system_7_6_media_media", "relation": "contains", "confidence": "EXTRACTED", "source_file": "docs/06_DESIGN_SYSTEM.md", "source_location": "L305", "weight": 1.0}, {"source": "docs_06_design_system_7_view_specifications", "target": "docs_06_design_system_7_7_inbox_inbox_p2", "relation": "contains", "confidence": "EXTRACTED", "source_file": "docs/06_DESIGN_SYSTEM.md", "source_location": "L309", "weight": 1.0}, {"source": "docs_06_design_system_7_view_specifications", "target": "docs_06_design_system_7_8_analytics_analytics", "relation": "contains", "confidence": "EXTRACTED", "source_file": "docs/06_DESIGN_SYSTEM.md", "source_location": "L313", "weight": 1.0}, {"source": "docs_06_design_system_7_view_specifications", "target": "docs_06_design_system_7_9_channels_channels", "relation": "contains", "confidence": "EXTRACTED", "source_file": "docs/06_DESIGN_SYSTEM.md", "source_location": "L317", "weight": 1.0}, {"source": "docs_06_design_system_7_view_specifications", "target": "docs_06_design_system_7_10_settings_store", "relation": "contains", "confidence": "EXTRACTED", "source_file": "docs/06_DESIGN_SYSTEM.md", "source_location": "L320", "weight": 1.0}, {"source": "docs_06_design_system_06_design_system_ux_specification", "target": "docs_06_design_system_8_interaction_patterns", "relation": "contains", "confidence": "EXTRACTED", "source_file": "docs/06_DESIGN_SYSTEM.md", "source_location": "L326", "weight": 1.0}, {"source": "docs_06_design_system_8_interaction_patterns", "target": "docs_06_design_system_8_1_loading_states", "relation": "contains", "confidence": "EXTRACTED", "source_file": "docs/06_DESIGN_SYSTEM.md", "source_location": "L328", "weight": 1.0}, {"source": "docs_06_design_system_8_interaction_patterns", "target": "docs_06_design_system_8_2_empty_states", "relation": "contains", "confidence": "EXTRACTED", "source_file": "docs/06_DESIGN_SYSTEM.md", "source_location": "L333", "weight": 1.0}, {"source": "docs_06_design_system_8_interaction_patterns", "target": "docs_06_design_system_8_3_error_states", "relation": "contains", "confidence": "EXTRACTED", "source_file": "docs/06_DESIGN_SYSTEM.md", "source_location": "L337", "weight": 1.0}, {"source": "docs_06_design_system_8_interaction_patterns", "target": "docs_06_design_system_8_4_toasts_sonner", "relation": "contains", "confidence": "EXTRACTED", "source_file": "docs/06_DESIGN_SYSTEM.md", "source_location": "L342", "weight": 1.0}, {"source": "docs_06_design_system_8_interaction_patterns", "target": "docs_06_design_system_8_5_confirmations", "relation": "contains", "confidence": "EXTRACTED", "source_file": "docs/06_DESIGN_SYSTEM.md", "source_location": "L346", "weight": 1.0}, {"source": "docs_06_design_system_8_interaction_patterns", "target": "docs_06_design_system_8_6_drag_and_drop", "relation": "contains", "confidence": "EXTRACTED", "source_file": "docs/06_DESIGN_SYSTEM.md", "source_location": "L350", "weight": 1.0}, {"source": "docs_06_design_system_8_interaction_patterns", "target": "docs_06_design_system_8_7_command_palette_cmd_k", "relation": "contains", "confidence": "EXTRACTED", "source_file": "docs/06_DESIGN_SYSTEM.md", "source_location": "L354", "weight": 1.0}, {"source": "docs_06_design_system_8_interaction_patterns", "target": "docs_06_design_system_8_8_realtime_feedback", "relation": "contains", "confidence": "EXTRACTED", "source_file": "docs/06_DESIGN_SYSTEM.md", "source_location": "L358", "weight": 1.0}, {"source": "docs_06_design_system_06_design_system_ux_specification", "target": "docs_06_design_system_9_accessibility_wcag_2_1_aa", "relation": "contains", "confidence": "EXTRACTED", "source_file": "docs/06_DESIGN_SYSTEM.md", "source_location": "L364", "weight": 1.0}, {"source": "docs_06_design_system_06_design_system_ux_specification", "target": "docs_06_design_system_10_responsive_breakpoints", "relation": "contains", "confidence": "EXTRACTED", "source_file": "docs/06_DESIGN_SYSTEM.md", "source_location": "L382", "weight": 1.0}, {"source": "docs_06_design_system_06_design_system_ux_specification", "target": "docs_06_design_system_11_content_voice_persian_ux_writing", "relation": "contains", "confidence": "EXTRACTED", "source_file": "docs/06_DESIGN_SYSTEM.md", "source_location": "L399", "weight": 1.0}, {"source": "docs_06_design_system_06_design_system_ux_specification", "target": "docs_06_design_system_12_iconography", "relation": "contains", "confidence": "EXTRACTED", "source_file": "docs/06_DESIGN_SYSTEM.md", "source_location": "L423", "weight": 1.0}, {"source": "docs_06_design_system_06_design_system_ux_specification", "target": "docs_06_design_system_appendix_a_token_quick_reference_from_globals_css", "relation": "contains", "confidence": "EXTRACTED", "source_file": "docs/06_DESIGN_SYSTEM.md", "source_location": "L435", "weight": 1.0}, {"source": "docs_06_design_system_06_design_system_ux_specification", "target": "docs_06_design_system_appendix_b_do_don_t", "relation": "contains", "confidence": "EXTRACTED", "source_file": "docs/06_DESIGN_SYSTEM.md", "source_location": "L457", "weight": 1.0}], "input_tokens": 0, "output_tokens": 0}